litecoin/__init__.py
litecoin/base58.py
litecoin/bech32.py
litecoin/bloom.py
litecoin/messages.py
litecoin/net.py
litecoin/rpc.py
litecoin/segwit_addr.py
litecoin/signature.py
litecoin/signmessage.py
litecoin/wallet.py
litecoin/core/__init__.py
litecoin/core/_bignum.py
litecoin/core/key.py
litecoin/core/script.py
litecoin/core/scripteval.py
litecoin/core/serialize.py
litecoin/core/contrib/__init__.py
litecoin/core/contrib/ripemd160.py
python_litecoinlib-0.12.0.dev0.dist-info/LICENSE
python_litecoinlib-0.12.0.dev0.dist-info/METADATA
python_litecoinlib-0.12.0.dev0.dist-info/WHEEL
python_litecoinlib-0.12.0.dev0.dist-info/top_level.txt
python_litecoinlib-0.12.0.dev0.dist-info/RECORD
