Metadata-Version: 2.1
Name: python-litecoinlib
Version: 0.12.0.dev0
Summary: The Swiss Army Knife of the Litecoin protocol.
Home-page: https://github.com/tannhausergate420/python-litecoinlib
Keywords: litecoin
Classifier: Programming Language :: Python
Classifier: License :: OSI Approved :: GNU Lesser General Public License v3 or later (LGPLv3+)
License-File: LICENSE
